{
	"variables": [],
	"info": {
		"name": "arquitectura",
		"_postman_id": "65f042e6-77a4-1da6-8a28-fde0e054764f",
		"description": "",
		"schema": "https://schema.getpostman.com/json/collection/v2.0.0/collection.json"
	},
	"item": [
		{
			"name": "users",
			"description": "",
			"item": [
				{
					"name": "POST USER",
					"request": {
						"url": "http://localhost:3000/users",
						"method": "POST",
						"header": [
							{
								"key": "Content-Type",
								"value": "application/json",
								"description": ""
							}
						],
						"body": {
							"mode": "raw",
							"raw": "{\n\t\"email\": \"javoescan@gmail.com\",\n\t\"firstname\": \"Javier\",\n\t\"lastname\": \"Escandarani\",\n\t\"document\": \"41758557\",\n\t\"role\": \"1\"\n}"
						},
						"description": ""
					},
					"response": []
				},
				{
					"name": "GET USERS",
					"request": {
						"url": "http://localhost:3000/users",
						"method": "GET",
						"header": [],
						"body": {},
						"description": ""
					},
					"response": []
				},
				{
					"name": "GET USER",
					"request": {
						"url": "http://localhost:3000/users/aaaaaa-bbbbbbb-ccccccc-ddddddd",
						"method": "GET",
						"header": [],
						"body": {},
						"description": ""
					},
					"response": []
				},
				{
					"name": "PUT USER",
					"request": {
						"url": "http://localhost:3000/users/aaaaaa-bbbbbbb-ccccccc-ddddddd",
						"method": "PUT",
						"header": [
							{
								"key": "Content-Type",
								"value": "application/json",
								"description": ""
							}
						],
						"body": {
							"mode": "raw",
							"raw": "{\n\t\"id\": \"aaaaaa-bbbbbbb-ccccccc-ddddddd\",\n\t\"email\": \"pepegonzalez@gmail.com\",\n\t\"firstname\": \"Pepe\",\n\t\"lastname\": \"Gonzalez\",\n\t\"document\": \"152343545\",\n\t\"role\": \"1\"\n}"
						},
						"description": ""
					},
					"response": []
				},
				{
					"name": "PATCH USER",
					"request": {
						"url": "http://localhost:3000/users/aaaaaa-bbbbbbb-ccccccc-ddddddd",
						"method": "PATCH",
						"header": [
							{
								"key": "Content-Type",
								"value": "application/json",
								"description": ""
							}
						],
						"body": {
							"mode": "raw",
							"raw": "{\n\t\"firstname\": \"Pepe2\",\n\t\"lastname\": \"Gonzalez2\"\n}"
						},
						"description": ""
					},
					"response": []
				},
				{
					"name": "DELETE USER",
					"request": {
						"url": "http://localhost:3000/users/d895038b-e299-4315-9026-4f02dae611cb",
						"method": "DELETE",
						"header": [
							{
								"key": "Content-Type",
								"value": "application/json",
								"description": ""
							}
						],
						"body": {
							"mode": "raw",
							"raw": ""
						},
						"description": ""
					},
					"response": []
				}
			]
		},
		{
			"name": "products",
			"description": "",
			"item": [
				{
					"name": "POST PRODUCT",
					"request": {
						"url": "http://localhost:3000/products",
						"method": "POST",
						"header": [
							{
								"key": "Content-Type",
								"value": "application/json",
								"description": ""
							}
						],
						"body": {
							"mode": "raw",
							"raw": "{\n\t\"name\": \"Producto1\",\n\t\"description\": \"Mi nuevo producto\",\n\t\"price\": 500\n}"
						},
						"description": ""
					},
					"response": []
				},
				{
					"name": "GET PRODUCTS",
					"request": {
						"url": "http://localhost:3000/products",
						"method": "GET",
						"header": [],
						"body": {},
						"description": ""
					},
					"response": []
				},
				{
					"name": "GET PRODUCT",
					"request": {
						"url": "http://localhost:3000/products/aaaaaa-bbbbbbb-ccccccc-ddddddd",
						"method": "GET",
						"header": [],
						"body": {},
						"description": ""
					},
					"response": []
				},
				{
					"name": "PUT PRODUCT",
					"request": {
						"url": "http://localhost:3000/products/aaaaaa-bbbbbbb-ccccccc-ddddddd",
						"method": "PUT",
						"header": [
							{
								"key": "Content-Type",
								"value": "application/json",
								"description": ""
							}
						],
						"body": {
							"mode": "raw",
							"raw": "{\n\t\"name\": \"Producto Actualizado\",\n\t\"description\": \"Mi nuevo producto\",\n\t\"price\": 500\n}"
						},
						"description": ""
					},
					"response": []
				},
				{
					"name": "PATCH PRODUCT",
					"request": {
						"url": "http://localhost:3000/products/aaaaaa-bbbbbbb-ccccccc-ddddddd",
						"method": "PATCH",
						"header": [
							{
								"key": "Content-Type",
								"value": "application/json",
								"description": ""
							}
						],
						"body": {
							"mode": "raw",
							"raw": "{\n\t\"name\": \"Producto Actualizado2\"\n}"
						},
						"description": ""
					},
					"response": []
				},
				{
					"name": "DELETE PRODUCT",
					"request": {
						"url": "http://localhost:3000/products/95a072b3-bf61-41c5-b81d-159b3994a734",
						"method": "DELETE",
						"header": [
							{
								"key": "Content-Type",
								"value": "application/json",
								"description": ""
							}
						],
						"body": {
							"mode": "raw",
							"raw": ""
						},
						"description": ""
					},
					"response": []
				}
			]
		},
		{
			"name": "sales",
			"description": "",
			"item": [
				{
					"name": "POST SALE",
					"request": {
						"url": "http://localhost:3000/sales",
						"method": "POST",
						"header": [
							{
								"key": "Content-Type",
								"value": "application/json",
								"description": ""
							}
						],
						"body": {
							"mode": "raw",
							"raw": "{\n\t\"products\": [{\"id\":\"aaaaaa-bbbbbbb-ccccccc-ddddddd\", \"price\": 20}],\n\t\"userId\": \"aaaaaa-bbbbbbb-ccccccc-ddddddd\",\n\t\"date\": 1604855534545,\n\t\"totalPrice\": 500\n}"
						},
						"description": ""
					},
					"response": []
				},
				{
					"name": "GET SALES",
					"request": {
						"url": "http://localhost:3000/sales",
						"method": "GET",
						"header": [],
						"body": {},
						"description": ""
					},
					"response": []
				},
				{
					"name": "GET SALES BY DATE",
					"request": {
						"url": {
							"raw": "http://localhost:3000/sales?from_date=\"2020-11-07\"&to_date=\"2020-11-09\"",
							"protocol": "http",
							"host": [
								"localhost"
							],
							"port": "3000",
							"path": [
								"sales"
							],
							"query": [
								{
									"key": "from_date",
									"value": "\"2020-11-07\"",
									"equals": true,
									"description": ""
								},
								{
									"key": "to_date",
									"value": "\"2020-11-09\"",
									"equals": true,
									"description": ""
								}
							],
							"variable": []
						},
						"method": "GET",
						"header": [],
						"body": {},
						"description": ""
					},
					"response": []
				},
				{
					"name": "GET SALES BY USER",
					"request": {
						"url": {
							"raw": "http://localhost:3000/sales/user/aaaaaa-bbbbbbb-ccccccc-ddddddd?from_date=\"2020-11-07\"&to_date=\"2020-11-09\"",
							"protocol": "http",
							"host": [
								"localhost"
							],
							"port": "3000",
							"path": [
								"sales",
								"user",
								"aaaaaa-bbbbbbb-ccccccc-ddddddd"
							],
							"query": [
								{
									"key": "from_date",
									"value": "\"2020-11-07\"",
									"equals": true,
									"description": ""
								},
								{
									"key": "to_date",
									"value": "\"2020-11-09\"",
									"equals": true,
									"description": ""
								}
							],
							"variable": []
						},
						"method": "GET",
						"header": [],
						"body": {},
						"description": ""
					},
					"response": []
				},
				{
					"name": "GET COMISSION",
					"request": {
						"url": {
							"raw": "http://localhost:3000/sales/user/aaaaaa-bbbbbbb-ccccccc-ddddddd/comissions?from_date=\"2020-11-07\"&to_date=\"2020-11-09\"",
							"protocol": "http",
							"host": [
								"localhost"
							],
							"port": "3000",
							"path": [
								"sales",
								"user",
								"aaaaaa-bbbbbbb-ccccccc-ddddddd",
								"comissions"
							],
							"query": [
								{
									"key": "from_date",
									"value": "\"2020-11-07\"",
									"equals": true,
									"description": ""
								},
								{
									"key": "to_date",
									"value": "\"2020-11-09\"",
									"equals": true,
									"description": ""
								}
							],
							"variable": []
						},
						"method": "GET",
						"header": [],
						"body": {},
						"description": ""
					},
					"response": []
				},
				{
					"name": "GET SALES BY PRODUCT",
					"request": {
						"url": {
							"raw": "http://localhost:3000/sales/product/aaaaaa-bbbbbbb-ccccccc-ddddddd?from_date=\"2020-11-07\"&to_date=\"2020-11-09\"",
							"protocol": "http",
							"host": [
								"localhost"
							],
							"port": "3000",
							"path": [
								"sales",
								"product",
								"aaaaaa-bbbbbbb-ccccccc-ddddddd"
							],
							"query": [
								{
									"key": "from_date",
									"value": "\"2020-11-07\"",
									"equals": true,
									"description": ""
								},
								{
									"key": "to_date",
									"value": "\"2020-11-09\"",
									"equals": true,
									"description": ""
								}
							],
							"variable": []
						},
						"method": "GET",
						"header": [],
						"body": {},
						"description": ""
					},
					"response": []
				},
				{
					"name": "GET SALE",
					"request": {
						"url": "http://localhost:3000/sales/aaaaaa-bbbbbbb-ccccccc-ddddddd",
						"method": "GET",
						"header": [],
						"body": {},
						"description": ""
					},
					"response": []
				},
				{
					"name": "PUT SALE",
					"request": {
						"url": "http://localhost:3000/sales/10c45b55-2716-4dae-9fa2-9c8835e791be",
						"method": "PUT",
						"header": [
							{
								"key": "Content-Type",
								"value": "application/json",
								"description": ""
							}
						],
						"body": {
							"mode": "raw",
							"raw": "{\n\t\"products\": [{\"id\":\"aaaaaa-bbbbbbb-ccccccc-ddddddd\", \"price\": 50}],\n\t\"userId\": \"aaaaaa-bbbbbbb-ccccccc-ddddddd\",\n\t\"date\": 1604855534545,\n\t\"totalPrice\": 100\n}"
						},
						"description": ""
					},
					"response": []
				},
				{
					"name": "PATCH SALE",
					"request": {
						"url": "http://localhost:3000/sales/aaaaaa-bbbbbbb-ccccccc-ddddddd",
						"method": "PATCH",
						"header": [
							{
								"key": "Content-Type",
								"value": "application/json",
								"description": ""
							}
						],
						"body": {
							"mode": "raw",
							"raw": "{\n\t\"totalPrice\": 250\n}"
						},
						"description": ""
					},
					"response": []
				},
				{
					"name": "DELETE SALE",
					"request": {
						"url": "http://localhost:3000/sales/b0ef85e7-58b2-4d63-9843-bd84a609ae18",
						"method": "DELETE",
						"header": [
							{
								"key": "Content-Type",
								"value": "application/json",
								"description": ""
							}
						],
						"body": {
							"mode": "raw",
							"raw": ""
						},
						"description": ""
					},
					"response": []
				}
			]
		}
	]
}